README.rst
pybench.py
setup.cfg
setup.py
pybench.egg-info/PKG-INFO
pybench.egg-info/SOURCES.txt
pybench.egg-info/dependency_links.txt
pybench.egg-info/top_level.txt