Metadata-Version: 1.1
Name: pybench
Version: 0.0.1
Summary: Benchmarking infrastructure for scientific codes
Home-page: https://github.com/firedrakeproject/pybench
Author: Florian Rathgeber
Author-email: florian.rathgeber@gmail.com
License: License :: OSI Approved :: BSD License
Platform: UNKNOWN
Classifier: Development Status :: 3 - Alpha
Classifier: Intended Audience :: Developers
Classifier: Intended Audience :: Science/Research
Classifier: License :: OSI Approved :: BSD License
Classifier: Operating System :: OS Independent
Classifier: Programming Language :: C
Classifier: Programming Language :: Cython
Classifier: Programming Language :: Python :: 2
Classifier: Programming Language :: Python :: 2.7
Classifier: Programming Language :: Python :: 3
Classifier: Programming Language :: Python :: 3.2
Classifier: Programming Language :: Python :: 3.3
Classifier: Programming Language :: Python :: 3.4
Classifier: Programming Language :: Python :: 3.5
